DictObject/__init__.py
DictObject/encoding.py
DictObject-0.1.2.dist-info/DESCRIPTION.rst
DictObject-0.1.2.dist-info/METADATA
DictObject-0.1.2.dist-info/metadata.json
DictObject-0.1.2.dist-info/RECORD
DictObject-0.1.2.dist-info/top_level.txt
DictObject-0.1.2.dist-info/WHEEL
